mbf_comparisons/__init__.py
mbf_comparisons/annotator.py
mbf_comparisons/comparisons.py
mbf_comparisons/methods.py
mbf_comparisons/venn.py
mbf_comparisons-0.1.dist-info/AUTHORS.rst
mbf_comparisons-0.1.dist-info/LICENSE.txt
mbf_comparisons-0.1.dist-info/METADATA
mbf_comparisons-0.1.dist-info/WHEEL
mbf_comparisons-0.1.dist-info/top_level.txt
mbf_comparisons-0.1.dist-info/RECORD
